[
  {
    "timestamp": "2026-05-02T13:56:27.903Z",
    "txHash": "0x46198b9dd071bc74c510ce415b161b4186562682b618d6c3c59ebf13100bb64f",
    "blockNumber": 2734829,
    "gasUsed": "35120",
    "success": true
  },
  {
    "timestamp": "2026-05-02T13:57:00.857Z",
    "txHash": "0x2aeab08a3f985b1dc69f85e70743ddcc34e26e513fb048d87dd3715feb2a2bf2",
    "blockNumber": 2734832,
    "gasUsed": "35120",
    "success": true
  },
  {
    "timestamp": "2026-05-02T13:57:36.571Z",
    "txHash": "0x4e08026de5e918d6395b83f9c4cc0ead0301420a418769047f254007ac13007f",
    "blockNumber": 2734835,
    "gasUsed": "35120",
    "success": true
  },
  {
    "timestamp": "2026-05-02T14:00:00.366Z",
    "txHash": "0x776c901b5bb4a2dea4e4101cef45a6f2f1b9f44c8ea3af0d83b675c9472cdd43",
    "blockNumber": 2734845,
    "gasUsed": "35120",
    "success": true
  },
  {
    "timestamp": "2026-05-02T14:03:00.614Z",
    "txHash": "0xd5504b360c4fdfd33726649712cf90f416c8480ef0e2310ebe14c4e4ea09c847",
    "blockNumber": 2734857,
    "gasUsed": "35120",
    "success": true
  },
  {
    "timestamp": "2026-05-02T14:07:03.927Z",
    "txHash": "0x8133669739e67347a1ac23df56886aae34edf845016f2bec9a69ba2fdc7bab95",
    "blockNumber": 2734875,
    "gasUsed": "35120",
    "success": true
  },
  {
    "timestamp": "2026-05-02T14:09:00.475Z",
    "txHash": "0x70e2c147b5234b6589ad92ae06d06dca2e49b47ccfea3551524fe64a1d8a2e50",
    "blockNumber": 2734885,
    "gasUsed": "35120",
    "success": true
  },
  {
    "timestamp": "2026-05-02T14:12:00.726Z",
    "txHash": "0xff7177b4160d0d734c24c0f4c68015a9454f77547c0d78459192ef5342910872",
    "blockNumber": 2734899,
    "gasUsed": "35120",
    "success": true
  },
  {
    "timestamp": "2026-05-02T14:15:00.987Z",
    "txHash": "0xc1e47e3fda4871284fea4d527a7c86ef76be432505ac1b22e6e09e27bbffd818",
    "blockNumber": 2734912,
    "gasUsed": "35120",
    "success": true
  },
  {
    "timestamp": "2026-05-02T14:18:00.226Z",
    "txHash": "0x7e3d00442a01cc9b754572edbb4fcd8653c71886e5de831fb87d8ee244ce0717",
    "blockNumber": 2734926,
    "gasUsed": "35120",
    "success": true
  },
  {
    "timestamp": "2026-05-02T14:21:00.435Z",
    "txHash": "0xb1d811ddba578916ae418637be722a4b0fe2833a41a35d92819b4bd0d72c4304",
    "blockNumber": 2734939,
    "gasUsed": "35120",
    "success": true
  },
  {
    "timestamp": "2026-05-02T14:28:45.362Z",
    "txHash": "0x6b6d2bd6c2386b0f0f6c44cc551c9e0d89d378373fcfb1ac97c03c03bc33f21c",
    "blockNumber": 2734973,
    "gasUsed": "35120",
    "success": true
  },
  {
    "timestamp": "2026-05-02T14:30:00.126Z",
    "txHash": "0x9e34c66e03f04e0e6fcca710f87e833720f959004d6689f2b85462666c177ee7",
    "blockNumber": 2734980,
    "gasUsed": "35120",
    "success": true
  },
  {
    "timestamp": "2026-05-02T14:33:00.373Z",
    "txHash": "0x056ece5797dad1423c08bca5d155ac933e89c1c8f68d3b4bc57076f0cc869035",
    "blockNumber": 2734992,
    "gasUsed": "35120",
    "success": true
  },
  {
    "timestamp": "2026-05-02T14:36:00.565Z",
    "txHash": "0x8adfb4de0342f0bad935093e345ea1aa2bd4967004e9e6648530fd6aae15cd9c",
    "blockNumber": 2735004,
    "gasUsed": "35120",
    "success": true
  },
  {
    "timestamp": "2026-05-02T14:39:00.767Z",
    "txHash": "0xc3dcd90c45d536b11fa029b268b1fe688c8f6296b53ab288f0936dd1913580a8",
    "blockNumber": 2735018,
    "gasUsed": "35120",
    "success": true
  },
  {
    "timestamp": "2026-05-02T14:41:45.040Z",
    "error": "missing revert data (action=\"estimateGas\", data=null, reason=null, transaction={ \"data\": \"0x3defb962\", \"from\": \"0x21c890c69aA54719EA6CAFAC4E0c1b044210D679\", \"to\": \"0x92fA6f0CaB84221f775b4FE2836ECEc1ECe8C119\" }, invocation=null, revert=null, code=CALL_EXCEPTION, version=6.16.0)",
    "success": false
  },
  {
    "timestamp": "2026-05-02T14:42:00.298Z",
    "error": "missing revert data (action=\"estimateGas\", data=null, reason=null, transaction={ \"data\": \"0x3defb962\", \"from\": \"0x21c890c69aA54719EA6CAFAC4E0c1b044210D679\", \"to\": \"0x92fA6f0CaB84221f775b4FE2836ECEc1ECe8C119\" }, invocation=null, revert=null, code=CALL_EXCEPTION, version=6.16.0)",
    "success": false
  },
  {
    "timestamp": "2026-05-02T14:43:19.556Z",
    "error": "missing revert data (action=\"estimateGas\", data=null, reason=null, transaction={ \"data\": \"0x3defb962\", \"from\": \"0x21c890c69aA54719EA6CAFAC4E0c1b044210D679\", \"to\": \"0x92fA6f0CaB84221f775b4FE2836ECEc1ECe8C119\" }, invocation=null, revert=null, code=CALL_EXCEPTION, version=6.16.0)",
    "success": false
  },
  {
    "timestamp": "2026-05-02T14:45:00.798Z",
    "error": "missing revert data (action=\"estimateGas\", data=null, reason=null, transaction={ \"data\": \"0x3defb962\", \"from\": \"0x21c890c69aA54719EA6CAFAC4E0c1b044210D679\", \"to\": \"0x92fA6f0CaB84221f775b4FE2836ECEc1ECe8C119\" }, invocation=null, revert=null, code=CALL_EXCEPTION, version=6.16.0)",
    "success": false
  },
  {
    "timestamp": "2026-05-02T14:48:00.997Z",
    "error": "missing revert data (action=\"estimateGas\", data=null, reason=null, transaction={ \"data\": \"0x3defb962\", \"from\": \"0x21c890c69aA54719EA6CAFAC4E0c1b044210D679\", \"to\": \"0x92fA6f0CaB84221f775b4FE2836ECEc1ECe8C119\" }, invocation=null, revert=null, code=CALL_EXCEPTION, version=6.16.0)",
    "success": false
  }
]